uuid32/__init__.py
uuid32/uuid32.py
uuid32-0.1.0.dist-info/METADATA
uuid32-0.1.0.dist-info/WHEEL
uuid32-0.1.0.dist-info/top_level.txt
uuid32-0.1.0.dist-info/RECORD
